<annotation>
	<folder>images</folder>
	<filename>qhaawkjucp 04_0.jpg</filename>
	<path>C:\tensorflow1\models\research\object_detection\images\qhaawkjucp 04_0.jpg</path>
	<source>
		<database>Unknown</database>
	</source>
	<size>
		<width>346</width>
		<height>489</height>
		<depth>3</depth>
	</size>
	<segmented>0</segmented>
	<object>
		<name>fl_f</name>
		<pose>Unspecified</pose>
		<truncated>0</truncated>
		<difficult>0</difficult>
		<bndbox>
			<xmin>126</xmin>
			<ymin>211</ymin>
			<xmax>158</xmax>
			<ymax>380</ymax>
		</bndbox>
	</object>
	<object>
		<name>fl_f</name>
		<pose>Unspecified</pose>
		<truncated>0</truncated>
		<difficult>0</difficult>
		<bndbox>
			<xmin>252</xmin>
			<ymin>225</ymin>
			<xmax>275</xmax>
			<ymax>279</ymax>
		</bndbox>
	</object>
</annotation>
